{
  "1": [
    [
      {
        "text": "Загрузить Пост",
        "callback_data": "1_Загрузить Пост"
      }
    ],
    [
      {
        "text": "Вопросы",
        "url": "https://t.me/absent_kai"
      }
    ]
  ],
  "2": [
    [
      {
        "text": "Да",
        "callback_data": "2_Да"
      },
      {
        "text": "Нет",
        "callback_data": "2_Нет"
      }
    ],
    [
      {
        "text": "Назад",
        "callback_data": "2_Назад"
      }
    ]
  ],
  "3": [
    [
      {
        "text": "в 'Начало'",
        "callback_data": "3_Вначало"
      }
    ]
  ],
  "4": [
    [
      {
        "text": "Да",
        "callback_data": "4_Да"
      },
      {
        "text": "Нет",
        "callback_data": "4_Нет"
      }
    ]
  ],
  "5": [
    [
      {
        "text": "По дням недели",
        "callback_data": "5_По дням недели"
      }
    ],
    [
      {
        "text": "Ежедневно",
        "callback_data": "5_Ежедневно"
      }
    ],
    [
      {
        "text": "Однократно",
        "callback_data": "5_Однократно"
      }
    ],
    [
      {
        "text": "Дата",
        "callback_data": "5_Дата"
      }
    ],
    [
      {
        "text": "в 'Начало'",
        "callback_data": "3_Вначало"
      }
    ]
  ],
  "7": [
    [
      {
        "text": "Да",
        "callback_data": "7_Да"
      },
      {
        "text": "Нет",
        "callback_data": "7_Нет"
      }
    ],
    [
      {
        "text": "Назад",
        "callback_data": "2_Назад"
      }
    ]
  ],
  "8": [
    [
      {
        "text": "Да",
        "callback_data": "8_Да"
      },
      {
        "text": "Нет",
        "callback_data": "8_Нет"
      }
    ],
    [
      {
        "text": "Назад",
        "callback_data": "2_Назад"
      }
    ]
  ],
  "9": [
    [
      {
        "text": "Понедельник",
        "callback_data": "5_Понедельник"
      }
    ],
    [
      {
        "text": "Вторник",
        "callback_data": "5_Вторник"
      }
    ],
    [
      {
        "text": "Среда",
        "callback_data": "5_Среда"
      }
    ],
    [
      {
        "text": "Четверг",
        "callback_data": "5_Четверг"
      }
    ],
    [
      {
        "text": "Пятница",
        "callback_data": "5_Пятница"
      }
    ],
    [
      {
        "text": "Суббота",
        "callback_data": "5_Суббота"
      }
    ],
    [
      {
        "text": "Воскресенье",
        "callback_data": "5_Воскресенье"
      }
    ],
    [
      {
        "text": "в 'Начало'",
        "callback_data": "3_Вначало"
      }
    ]
  ],
  "100": [
    [
      {
        "text": "Удалить Тексты",
        "callback_data": "100_Удалить Тексты"
      },
      {
        "text": "Удалить Файлы",
        "callback_data": "100_Удалить Файлы"
      }
    ],
    [
      {
        "text": "Публиковать Тексты",
        "callback_data": "100_Публиковать Тексты"
      },
      {
        "text": "Публиковать Файлы",
        "callback_data": "100_Публиковать Файлы"
      }
    ],
    [
      {
        "text": "Назад",
        "callback_data": "3_Вначало"
      }
    ]
  ],
  "101": [
    [
      {
        "text": "Да",
        "callback_data": "101_Да"
      },
      {
        "text": "Нет",
        "callback_data": "101_Нет"
      }
    ],
    [
      {
        "text": "Назад",
        "callback_data": "1_Админ Бота"
      }
    ]
  ],
  "102": [
    [
      {
        "text": "Назад",
        "callback_data": "1_Админ Бота"
      }
    ]
  ],
  "103": [
    [
      {
        "text": "Да",
        "callback_data": "103_Да"
      },
      {
        "text": "Нет",
        "callback_data": "103_Нет"
      }
    ],
    [
      {
        "text": "Назад",
        "callback_data": "1_Админ Бота"
      }
    ]
  ],
  "104": [
    [
      {
        "text": "Да",
        "callback_data": "104_Да"
      },
      {
        "text": "Нет",
        "callback_data": "104_Нет"
      }
    ],
    [
      {
        "text": "Назад",
        "callback_data": "1_Админ Бота"
      }
    ]
  ],
  "105": [
    [
      {
        "text": "Да",
        "callback_data": "105_Да"
      },
      {
        "text": "Нет",
        "callback_data": "105_Нет"
      }
    ],
    [
      {
        "text": "Назад",
        "callback_data": "1_Админ Бота"
      }
    ]
  ],
  "adm1": [
    [
      {
        "text": "Загрузить Пост",
        "callback_data": "1_Загрузить Пост"
      }
    ],
    [
      {
        "text": "Удалить Пост",
        "callback_data": "1_Удалить Пост"
      }
    ],
    [
      {
        "text": "Вопросы",
        "url": "https://t.me/absent_kai"
      }
    ],
    [
      {
        "text": "Модерация Постов",
        "callback_data": "1_Админ Бота"
      }
    ]
  ]
}